inaturalist/__init__.py
inaturalist/cli.py
inaturalist/github_actions_strategy.py
inaturalist/scraper.py
inaturalist-0.1.10.dist-info/entry_points.txt
inaturalist-0.1.10.dist-info/LICENSE
inaturalist-0.1.10.dist-info/WHEEL
inaturalist-0.1.10.dist-info/METADATA
inaturalist-0.1.10.dist-info/RECORD
