Metadata-Version: 2.1
Name: inaturalist
Version: 0.1.10
Summary: iNaturalist Photo Scraper
License: MIT
Author: Alyetama
Author-email: malyetama@pm.me
Requires-Python: >=3.7,<4.0
Classifier: License :: OSI Approved :: MIT License
Classifier: Programming Language :: Python :: 3
Classifier: Programming Language :: Python :: 3.10
Classifier: Programming Language :: Python :: 3.7
Classifier: Programming Language :: Python :: 3.8
Classifier: Programming Language :: Python :: 3.9
Requires-Dist: loguru (>=0.6.0)
Requires-Dist: minio (>=7.1.10)
Requires-Dist: python-dotenv (>=0.20.0)
Requires-Dist: requests (>=2.28.1)
